MANIFEST.in
README.md
setup.py
astrohut/__init__.py
astrohut.egg-info/PKG-INFO
astrohut.egg-info/SOURCES.txt
astrohut.egg-info/dependency_links.txt
astrohut.egg-info/requires.txt
astrohut.egg-info/top_level.txt
astrohut/core/__init__.py
astrohut/core/box2d.c
astrohut/core/box2d.h
astrohut/core/box3d.c
astrohut/core/box3d.h
astrohut/core/common.c
astrohut/core/common.h
astrohut/core/cons.c
astrohut/core/cons.h
astrohut/core/constants.py
astrohut/core/core.py
astrohut/core/interface.py
astrohut/core/structs2d.py
astrohut/core/structs3d.py
astrohut/examples/__init__.py
astrohut/examples/collision3d.py
astrohut/examples/disk3d.py
astrohut/examples/energy.py
astrohut/examples/random2d.py
astrohut/examples/random3d.py